flask_image_search/__about__.py
flask_image_search/__init__.py
Flask_Image_Search-1.0.1.dist-info/LICENSE
Flask_Image_Search-1.0.1.dist-info/METADATA
Flask_Image_Search-1.0.1.dist-info/WHEEL
Flask_Image_Search-1.0.1.dist-info/top_level.txt
Flask_Image_Search-1.0.1.dist-info/RECORD
