Metadata-Version: 2.1
Name: Flask-Image-Search
Version: 1.0.1
Summary: Image Searching For Flask and Flask-SQLAlchemy.
Home-page: https://flask-image-search.readthedocs.io
Author: Hanan Fokkens
Author-email: hananfokkens@gmail.com
License: MIT license
Platform: UNKNOWN
Classifier: Development Status :: 5 - Production/Stable
Classifier: Intended Audience :: Developers
Classifier: License :: OSI Approved :: MIT License
Classifier: Natural Language :: English
Classifier: Programming Language :: Python :: 3
Classifier: Programming Language :: Python :: 3.6
Classifier: Programming Language :: Python :: 3.7
Classifier: Programming Language :: Python :: 3.8
Classifier: Programming Language :: Python :: 3.9
Classifier: Programming Language :: Python :: 3 :: Only
Requires-Python: >=3.6
License-File: LICENSE
Requires-Dist: tensorflow (==2.2.1)
Requires-Dist: Keras (==2.3.1)
Requires-Dist: flask (>=1.0.4)
Requires-Dist: Flask-SQLAlchemy (>=2.5.0)
Requires-Dist: pillow (>=8.2.0)
Requires-Dist: zarr (>=2.8.1)
Provides-Extra: dev
Requires-Dist: flake8 ; extra == 'dev'
Requires-Dist: coverage ; extra == 'dev'
Requires-Dist: sphinx ; extra == 'dev'
Requires-Dist: twine ; extra == 'dev'
Requires-Dist: pytest ; extra == 'dev'
Requires-Dist: pallets-sphinx-themes ; extra == 'dev'
Provides-Extra: docs
Requires-Dist: pallets-sphinx-themes ; extra == 'docs'
